[
  {
    "match": "st gallen vs benfica",
    "sport": "Football",
    "type": "3-way",
    "profit_percent": 46.25,
    "profit_ugx": 46253,
    "total_stake": 100000,
    "arb_sum": 0.5375,
    "bets": [
      {
        "bookmaker": "Melbet",
        "outcome": "Home",
        "odd": 7.02,
        "stake": 26504,
        "win": 186058
      },
      {
        "bookmaker": "Fortebet",
        "outcome": "Draw",
        "odd": 5.6,
        "stake": 33224,
        "win": 186054
      },
      {
        "bookmaker": "22Bet",
        "outcome": "Away",
        "odd": 4.62,
        "stake": 40272,
        "win": 186057
      }
    ],
    "market_type": "1x2",
    "market_specifier": ""
  },
  {
    "match": "st gallen vs benfica",
    "sport": "Football",
    "type": "Asian Handicap -0.5",
    "profit_percent": 14.39,
    "profit_ugx": 14385,
    "total_stake": 100000,
    "arb_sum": 0.8561,
    "bets": [
      {
        "bookmaker": "ChampionBet",
        "outcome": "AH -0.5 (Home)",
        "odd": 2.76,
        "stake": 42320,
        "win": 116803
      },
      {
        "bookmaker": "1xBet",
        "outcome": "AH -0.5 (Away)",
        "odd": 2.025,
        "stake": 57680,
        "win": 116802
      }
    ],
    "market_type": "1x2",
    "market_specifier": ""
  },
  {
    "match": "st gallen vs benfica",
    "sport": "Football",
    "type": "Asian Handicap -0.5",
    "profit_percent": 14.14,
    "profit_ugx": 14140,
    "total_stake": 100000,
    "arb_sum": 0.8586,
    "bets": [
      {
        "bookmaker": "ChampionBet",
        "outcome": "AH -0.5 (Home)",
        "odd": 2.76,
        "stake": 42199,
        "win": 116469
      },
      {
        "bookmaker": "22Bet",
        "outcome": "AH -0.5 (Away)",
        "odd": 2.015,
        "stake": 57801,
        "win": 116469
      }
    ],
    "market_type": "1x2",
    "market_specifier": ""
  },
  {
    "match": "st gallen vs benfica",
    "sport": "Football",
    "type": "Asian Handicap -0.5",
    "profit_percent": 14.39,
    "profit_ugx": 14385,
    "total_stake": 100000,
    "arb_sum": 0.8561,
    "bets": [
      {
        "bookmaker": "ChampionBet",
        "outcome": "AH -0.5 (Home)",
        "odd": 2.76,
        "stake": 42320,
        "win": 116803
      },
      {
        "bookmaker": "1xBet",
        "outcome": "AH -0.5 (Away)",
        "odd": 2.025,
        "stake": 57680,
        "win": 116802
      }
    ],
    "market_type": "1x2",
    "market_specifier": ""
  },
  {
    "match": "st gallen vs benfica",
    "sport": "Football",
    "type": "Asian Handicap -0.5",
    "profit_percent": 14.14,
    "profit_ugx": 14140,
    "total_stake": 100000,
    "arb_sum": 0.8586,
    "bets": [
      {
        "bookmaker": "ChampionBet",
        "outcome": "AH -0.5 (Home)",
        "odd": 2.76,
        "stake": 42199,
        "win": 116469
      },
      {
        "bookmaker": "22Bet",
        "outcome": "AH -0.5 (Away)",
        "odd": 2.015,
        "stake": 57801,
        "win": 116469
      }
    ],
    "market_type": "1x2",
    "market_specifier": ""
  },
  {
    "match": "twente vs ferencvaros",
    "sport": "Football",
    "type": "3-way",
    "profit_percent": 1.05,
    "profit_ugx": 1054,
    "total_stake": 100000,
    "arb_sum": 0.9895,
    "bets": [
      {
        "bookmaker": "Melbet",
        "outcome": "Home",
        "odd": 1.553,
        "stake": 65077,
        "win": 101065
      },
      {
        "bookmaker": "22Bet",
        "outcome": "Draw",
        "odd": 5.68,
        "stake": 17793,
        "win": 101064
      },
      {
        "bookmaker": "Fortebet",
        "outcome": "Away",
        "odd": 5.9,
        "stake": 17130,
        "win": 101067
      }
    ],
    "market_type": "1x2",
    "market_specifier": ""
  },
  {
    "match": "paks vs panathinaikos",
    "sport": "Football",
    "type": "3-way",
    "profit_percent": 33.59,
    "profit_ugx": 33587,
    "total_stake": 100000,
    "arb_sum": 0.6641,
    "bets": [
      {
        "bookmaker": "Melbet",
        "outcome": "Home",
        "odd": 5.14,
        "stake": 29294,
        "win": 150571
      },
      {
        "bookmaker": "AbaBet",
        "outcome": "Draw",
        "odd": 4.2,
        "stake": 35851,
        "win": 150574
      },
      {
        "bookmaker": "22Bet",
        "outcome": "Away",
        "odd": 4.32,
        "stake": 34855,
        "win": 150574
      }
    ],
    "market_type": "1x2",
    "market_specifier": ""
  },
  {
    "match": "polissya zhytomyr vs copenhagen",
    "sport": "Football",
    "type": "3-way",
    "profit_percent": 20.68,
    "profit_ugx": 20683,
    "total_stake": 100000,
    "arb_sum": 0.7932,
    "bets": [
      {
        "bookmaker": "Melbet",
        "outcome": "Home",
        "odd": 3.7,
        "stake": 34075,
        "win": 126078
      },
      {
        "bookmaker": "Fortebet",
        "outcome": "Draw",
        "odd": 3.85,
        "stake": 32747,
        "win": 126076
      },
      {
        "bookmaker": "22Bet",
        "outcome": "Away",
        "odd": 3.8,
        "stake": 33178,
        "win": 126076
      }
    ],
    "market_type": "1x2",
    "market_specifier": ""
  },
  {
    "match": "varazdin vs jablonec",
    "sport": "Football",
    "type": "3-way",
    "profit_percent": 1.97,
    "profit_ugx": 1972,
    "total_stake": 100000,
    "arb_sum": 0.9803,
    "bets": [
      {
        "bookmaker": "Melbet",
        "outcome": "Home",
        "odd": 2.68,
        "stake": 38064,
        "win": 102012
      },
      {
        "bookmaker": "Fortebet",
        "outcome": "Draw",
        "odd": 3.35,
        "stake": 30451,
        "win": 102011
      },
      {
        "bookmaker": "22Bet",
        "outcome": "Away",
        "odd": 3.24,
        "stake": 31485,
        "win": 102011
      }
    ],
    "market_type": "1x2",
    "market_specifier": ""
  },
  {
    "match": "vojvodina vs ajax",
    "sport": "Football",
    "type": "3-way",
    "profit_percent": 29.08,
    "profit_ugx": 29077,
    "total_stake": 100000,
    "arb_sum": 0.7092,
    "bets": [
      {
        "bookmaker": "Melbet",
        "outcome": "Home",
        "odd": 4.22,
        "stake": 33412,
        "win": 140999
      },
      {
        "bookmaker": "Fortebet",
        "outcome": "Draw",
        "odd": 4.25,
        "stake": 33176,
        "win": 140998
      },
      {
        "bookmaker": "22Bet",
        "outcome": "Away",
        "odd": 4.22,
        "stake": 33412,
        "win": 140999
      }
    ],
    "market_type": "1x2",
    "market_specifier": ""
  },
  {
    "match": "hapoel tel aviv vs ludogorets",
    "sport": "Football",
    "type": "3-way",
    "profit_percent": 7.69,
    "profit_ugx": 7694,
    "total_stake": 100000,
    "arb_sum": 0.9231,
    "bets": [
      {
        "bookmaker": "Melbet",
        "outcome": "Home",
        "odd": 3.355,
        "stake": 32291,
        "win": 108336
      },
      {
        "bookmaker": "AbaBet",
        "outcome": "Draw",
        "odd": 3.2,
        "stake": 33855,
        "win": 108336
      },
      {
        "bookmaker": "22Bet",
        "outcome": "Away",
        "odd": 3.2,
        "stake": 33855,
        "win": 108336
      }
    ],
    "market_type": "1x2",
    "market_specifier": ""
  },
  {
    "match": "lugano vs dukagjini",
    "sport": "Football",
    "type": "3-way",
    "profit_percent": 2.51,
    "profit_ugx": 2510,
    "total_stake": 100000,
    "arb_sum": 0.9749,
    "bets": [
      {
        "bookmaker": "AbaBet",
        "outcome": "Home",
        "odd": 1.17,
        "stake": 87671,
        "win": 102575
      },
      {
        "bookmaker": "Melbet",
        "outcome": "Draw",
        "odd": 14.8,
        "stake": 6931,
        "win": 102579
      },
      {
        "bookmaker": "Fortebet",
        "outcome": "Away",
        "odd": 19.0,
        "stake": 5399,
        "win": 102581
      }
    ],
    "market_type": "1x2",
    "market_specifier": ""
  },
  {
    "match": "zilina vs gks katowice",
    "sport": "Football",
    "type": "3-way",
    "profit_percent": 4.56,
    "profit_ugx": 4564,
    "total_stake": 100000,
    "arb_sum": 0.9544,
    "bets": [
      {
        "bookmaker": "Melbet",
        "outcome": "Home",
        "odd": 2.67,
        "stake": 39244,
        "win": 104781
      },
      {
        "bookmaker": "Fortebet",
        "outcome": "Draw",
        "odd": 3.4,
        "stake": 30818,
        "win": 104781
      },
      {
        "bookmaker": "22Bet",
        "outcome": "Away",
        "odd": 3.5,
        "stake": 29938,
        "win": 104783
      }
    ],
    "market_type": "1x2",
    "market_specifier": ""
  },
  {
    "match": "nsi runavik vs koper",
    "sport": "Football",
    "type": "3-way",
    "profit_percent": 4.65,
    "profit_ugx": 4653,
    "total_stake": 100000,
    "arb_sum": 0.9535,
    "bets": [
      {
        "bookmaker": "Fortebet",
        "outcome": "Home",
        "odd": 2.79,
        "stake": 37591,
        "win": 104879
      },
      {
        "bookmaker": "AbaBet",
        "outcome": "Draw",
        "odd": 3.25,
        "stake": 32271,
        "win": 104881
      },
      {
        "bookmaker": "Melbet",
        "outcome": "Away",
        "odd": 3.48,
        "stake": 30138,
        "win": 104880
      }
    ],
    "market_type": "1x2",
    "market_specifier": ""
  },
  {
    "match": "rijeka vs derry",
    "sport": "Football",
    "type": "3-way",
    "profit_percent": 3.55,
    "profit_ugx": 3552,
    "total_stake": 100000,
    "arb_sum": 0.9645,
    "bets": [
      {
        "bookmaker": "AbaBet",
        "outcome": "Home",
        "odd": 1.17,
        "stake": 88618,
        "win": 103683
      },
      {
        "bookmaker": "Melbet",
        "outcome": "Draw",
        "odd": 17.5,
        "stake": 5925,
        "win": 103688
      },
      {
        "bookmaker": "Fortebet",
        "outcome": "Away",
        "odd": 19.0,
        "stake": 5457,
        "win": 103683
      }
    ],
    "market_type": "1x2",
    "market_specifier": ""
  },
  {
    "match": "shelbourne vs kalju",
    "sport": "Football",
    "type": "3-way",
    "profit_percent": 2.07,
    "profit_ugx": 2067,
    "total_stake": 100000,
    "arb_sum": 0.9793,
    "bets": [
      {
        "bookmaker": "Melbet",
        "outcome": "Home",
        "odd": 1.42,
        "stake": 71909,
        "win": 102111
      },
      {
        "bookmaker": "22Bet",
        "outcome": "Draw",
        "odd": 7.24,
        "stake": 14104,
        "win": 102113
      },
      {
        "bookmaker": "Fortebet",
        "outcome": "Away",
        "odd": 7.3,
        "stake": 13988,
        "win": 102112
      }
    ],
    "market_type": "1x2",
    "market_specifier": ""
  },
  {
    "match": "stjarnan vs ilves",
    "sport": "Football",
    "type": "3-way",
    "profit_percent": 7.22,
    "profit_ugx": 7216,
    "total_stake": 100000,
    "arb_sum": 0.9278,
    "bets": [
      {
        "bookmaker": "Melbet",
        "outcome": "Home",
        "odd": 2.41,
        "stake": 44721,
        "win": 107778
      },
      {
        "bookmaker": "Fortebet",
        "outcome": "Draw",
        "odd": 3.95,
        "stake": 27285,
        "win": 107776
      },
      {
        "bookmaker": "22Bet",
        "outcome": "Away",
        "odd": 3.85,
        "stake": 27994,
        "win": 107777
      }
    ],
    "market_type": "1x2",
    "market_specifier": ""
  },
  {
    "match": "valur vs zrinjski",
    "sport": "Football",
    "type": "3-way",
    "profit_percent": 6.71,
    "profit_ugx": 6711,
    "total_stake": 100000,
    "arb_sum": 0.9329,
    "bets": [
      {
        "bookmaker": "Melbet",
        "outcome": "Home",
        "odd": 2.866,
        "stake": 37402,
        "win": 107194
      },
      {
        "bookmaker": "Fortebet",
        "outcome": "Draw",
        "odd": 3.4,
        "stake": 31528,
        "win": 107195
      },
      {
        "bookmaker": "22Bet",
        "outcome": "Away",
        "odd": 3.45,
        "stake": 31071,
        "win": 107195
      }
    ],
    "market_type": "1x2",
    "market_specifier": ""
  },
  {
    "match": "bolivar vs gremio",
    "sport": "Football",
    "type": "3-way",
    "profit_percent": 0.99,
    "profit_ugx": 995,
    "total_stake": 100000,
    "arb_sum": 0.9901,
    "bets": [
      {
        "bookmaker": "Melbet",
        "outcome": "Home",
        "odd": 1.65,
        "stake": 61215,
        "win": 101005
      },
      {
        "bookmaker": "1xBet",
        "outcome": "Draw",
        "odd": 5.12,
        "stake": 19727,
        "win": 101002
      },
      {
        "bookmaker": "Fortebet",
        "outcome": "Away",
        "odd": 5.3,
        "stake": 19058,
        "win": 101007
      }
    ],
    "market_type": "1x2",
    "market_specifier": ""
  },
  {
    "match": "boca juniors vs ohiggins",
    "sport": "Football",
    "type": "3-way",
    "profit_percent": 3.99,
    "profit_ugx": 3986,
    "total_stake": 100000,
    "arb_sum": 0.9601,
    "bets": [
      {
        "bookmaker": "Melbet",
        "outcome": "Home",
        "odd": 1.3,
        "stake": 80117,
        "win": 104152
      },
      {
        "bookmaker": "22Bet",
        "outcome": "Draw",
        "odd": 10.0,
        "stake": 10415,
        "win": 104150
      },
      {
        "bookmaker": "Fortebet",
        "outcome": "Away",
        "odd": 11.0,
        "stake": 9468,
        "win": 104148
      }
    ],
    "market_type": "1x2",
    "market_specifier": ""
  },
  {
    "match": "santa fe vs caracas",
    "sport": "Football",
    "type": "3-way",
    "profit_percent": 6.71,
    "profit_ugx": 6710,
    "total_stake": 100000,
    "arb_sum": 0.9329,
    "bets": [
      {
        "bookmaker": "Fortebet",
        "outcome": "Home",
        "odd": 1.36,
        "stake": 78818,
        "win": 107192
      },
      {
        "bookmaker": "1xBet",
        "outcome": "Draw",
        "odd": 11.4,
        "stake": 9403,
        "win": 107194
      },
      {
        "bookmaker": "ChampionBet",
        "outcome": "Away",
        "odd": 9.1,
        "stake": 11779,
        "win": 107189
      }
    ],
    "market_type": "1x2",
    "market_specifier": ""
  },
  {
    "match": "cordoba vs sevilla",
    "sport": "Football",
    "type": "3-way",
    "profit_percent": 10.61,
    "profit_ugx": 10611,
    "total_stake": 100000,
    "arb_sum": 0.8939,
    "bets": [
      {
        "bookmaker": "Fortebet",
        "outcome": "Home",
        "odd": 2.86,
        "stake": 39115,
        "win": 111869
      },
      {
        "bookmaker": "AbaBet",
        "outcome": "Draw",
        "odd": 3.7,
        "stake": 30235,
        "win": 111870
      },
      {
        "bookmaker": "1xBet",
        "outcome": "Away",
        "odd": 3.65,
        "stake": 30649,
        "win": 111869
      }
    ],
    "market_type": "1x2",
    "market_specifier": ""
  },
  {
    "match": "st gallen vs benfica",
    "sport": "Football",
    "type": "Double Chance 1X",
    "profit_percent": 17.62,
    "profit_ugx": 17619,
    "total_stake": 100000,
    "arb_sum": 0.8238,
    "bets": [
      {
        "bookmaker": "22Bet",
        "outcome": "1X",
        "odd": 2.755,
        "stake": 44061,
        "win": 121388
      },
      {
        "bookmaker": "1xBet",
        "outcome": "X2",
        "odd": 2.17,
        "stake": 55939,
        "win": 121388
      }
    ],
    "market_type": "1x2",
    "market_specifier": ""
  },
  {
    "match": "st gallen vs benfica",
    "sport": "Football",
    "type": "Double Chance 1X",
    "profit_percent": 17.62,
    "profit_ugx": 17619,
    "total_stake": 100000,
    "arb_sum": 0.8238,
    "bets": [
      {
        "bookmaker": "22Bet",
        "outcome": "1X",
        "odd": 2.755,
        "stake": 44061,
        "win": 121388
      },
      {
        "bookmaker": "1xBet",
        "outcome": "X2",
        "odd": 2.17,
        "stake": 55939,
        "win": 121388
      }
    ],
    "market_type": "1x2",
    "market_specifier": ""
  },
  {
    "match": "paksi vs panathinaikos",
    "sport": "Football",
    "type": "Double Chance 1X",
    "profit_percent": 6.23,
    "profit_ugx": 6228,
    "total_stake": 100000,
    "arb_sum": 0.9377,
    "bets": [
      {
        "bookmaker": "22Bet",
        "outcome": "1X",
        "odd": 2.325,
        "stake": 45867,
        "win": 106641
      },
      {
        "bookmaker": "1xBet",
        "outcome": "X2",
        "odd": 1.97,
        "stake": 54133,
        "win": 106642
      }
    ],
    "market_type": "1x2",
    "market_specifier": ""
  },
  {
    "match": "paksi vs panathinaikos",
    "sport": "Football",
    "type": "Double Chance 1X",
    "profit_percent": 6.23,
    "profit_ugx": 6228,
    "total_stake": 100000,
    "arb_sum": 0.9377,
    "bets": [
      {
        "bookmaker": "22Bet",
        "outcome": "1X",
        "odd": 2.325,
        "stake": 45867,
        "win": 106641
      },
      {
        "bookmaker": "1xBet",
        "outcome": "X2",
        "odd": 1.97,
        "stake": 54133,
        "win": 106642
      }
    ],
    "market_type": "1x2",
    "market_specifier": ""
  },
  {
    "match": "vojvodina novi sad vs ajax",
    "sport": "Football",
    "type": "Double Chance 1X",
    "profit_percent": 6.08,
    "profit_ugx": 6085,
    "total_stake": 100000,
    "arb_sum": 0.9392,
    "bets": [
      {
        "bookmaker": "22Bet",
        "outcome": "1X",
        "odd": 2.1,
        "stake": 50704,
        "win": 106478
      },
      {
        "bookmaker": "1xBet",
        "outcome": "X2",
        "odd": 2.16,
        "stake": 49296,
        "win": 106479
      }
    ],
    "market_type": "1x2",
    "market_specifier": ""
  },
  {
    "match": "vojvodina novi sad vs ajax",
    "sport": "Football",
    "type": "Double Chance 1X",
    "profit_percent": 6.08,
    "profit_ugx": 6085,
    "total_stake": 100000,
    "arb_sum": 0.9392,
    "bets": [
      {
        "bookmaker": "22Bet",
        "outcome": "1X",
        "odd": 2.1,
        "stake": 50704,
        "win": 106478
      },
      {
        "bookmaker": "1xBet",
        "outcome": "X2",
        "odd": 2.16,
        "stake": 49296,
        "win": 106479
      }
    ],
    "market_type": "1x2",
    "market_specifier": ""
  }
]