[
  {
    "match": "malisheva vs hibernian",
    "sport": "Football",
    "type": "3-way",
    "profit_percent": 33.37,
    "profit_ugx": 33375,
    "total_stake": 100000,
    "arb_sum": 0.6663,
    "bets": [
      {
        "bookmaker": "Fortebet",
        "outcome": "Home",
        "odd": 5.7,
        "stake": 26332,
        "win": 150092
      },
      {
        "bookmaker": "AbaBet",
        "outcome": "Draw",
        "odd": 4.1,
        "stake": 36608,
        "win": 150093
      },
      {
        "bookmaker": "1xBet",
        "outcome": "Away",
        "odd": 4.05,
        "stake": 37060,
        "win": 150093
      }
    ],
    "market_type": "1x2",
    "market_specifier": ""
  },
  {
    "match": "malisheva vs hibernian",
    "sport": "Football",
    "type": "Asian Handicap -0.5",
    "profit_percent": 14.16,
    "profit_ugx": 14162,
    "total_stake": 100000,
    "arb_sum": 0.8584,
    "bets": [
      {
        "bookmaker": "ChampionBet",
        "outcome": "AH -0.5 (Home)",
        "odd": 2.32,
        "stake": 50215,
        "win": 116499
      },
      {
        "bookmaker": "1xBet",
        "outcome": "AH -0.5 (Away)",
        "odd": 2.34,
        "stake": 49785,
        "win": 116497
      }
    ],
    "market_type": "1x2",
    "market_specifier": ""
  },
  {
    "match": "malisheva vs hibernian",
    "sport": "Football",
    "type": "Asian Handicap -0.5",
    "profit_percent": 14.16,
    "profit_ugx": 14162,
    "total_stake": 100000,
    "arb_sum": 0.8584,
    "bets": [
      {
        "bookmaker": "ChampionBet",
        "outcome": "AH -0.5 (Home)",
        "odd": 2.32,
        "stake": 50215,
        "win": 116499
      },
      {
        "bookmaker": "1xBet",
        "outcome": "AH -0.5 (Away)",
        "odd": 2.34,
        "stake": 49785,
        "win": 116497
      }
    ],
    "market_type": "1x2",
    "market_specifier": ""
  },
  {
    "match": "alashkert vs cfr cluj",
    "sport": "Football",
    "type": "3-way",
    "profit_percent": 9.8,
    "profit_ugx": 9795,
    "total_stake": 100000,
    "arb_sum": 0.902,
    "bets": [
      {
        "bookmaker": "Fortebet",
        "outcome": "Home",
        "odd": 3.5,
        "stake": 31674,
        "win": 110859
      },
      {
        "bookmaker": "AbaBet",
        "outcome": "Draw",
        "odd": 3.25,
        "stake": 34110,
        "win": 110858
      },
      {
        "bookmaker": "1xBet",
        "outcome": "Away",
        "odd": 3.24,
        "stake": 34216,
        "win": 110860
      }
    ],
    "market_type": "1x2",
    "market_specifier": ""
  },
  {
    "match": "fk liepaja vs austria vienna",
    "sport": "Football",
    "type": "3-way",
    "profit_percent": 43.32,
    "profit_ugx": 43318,
    "total_stake": 100000,
    "arb_sum": 0.5668,
    "bets": [
      {
        "bookmaker": "Fortebet",
        "outcome": "Home",
        "odd": 7.6,
        "stake": 23213,
        "win": 176419
      },
      {
        "bookmaker": "AbaBet",
        "outcome": "Draw",
        "odd": 4.75,
        "stake": 37141,
        "win": 176420
      },
      {
        "bookmaker": "1xBet",
        "outcome": "Away",
        "odd": 4.45,
        "stake": 39645,
        "win": 176420
      }
    ],
    "market_type": "1x2",
    "market_specifier": ""
  },
  {
    "match": "fk panevezys vs tobol",
    "sport": "Football",
    "type": "3-way",
    "profit_percent": 10.58,
    "profit_ugx": 10579,
    "total_stake": 100000,
    "arb_sum": 0.8942,
    "bets": [
      {
        "bookmaker": "Fortebet",
        "outcome": "Home",
        "odd": 3.25,
        "stake": 34409,
        "win": 111829
      },
      {
        "bookmaker": "AbaBet",
        "outcome": "Draw",
        "odd": 3.4,
        "stake": 32891,
        "win": 111829
      },
      {
        "bookmaker": "1xBet",
        "outcome": "Away",
        "odd": 3.42,
        "stake": 32699,
        "win": 111831
      }
    ],
    "market_type": "1x2",
    "market_specifier": ""
  },
  {
    "match": "qarabag vs cska sofia",
    "sport": "Football",
    "type": "3-way",
    "profit_percent": 0.8,
    "profit_ugx": 801,
    "total_stake": 100000,
    "arb_sum": 0.992,
    "bets": [
      {
        "bookmaker": "Melbet",
        "outcome": "Home",
        "odd": 1.46,
        "stake": 69046,
        "win": 100807
      },
      {
        "bookmaker": "22Bet",
        "outcome": "Draw",
        "odd": 6.8,
        "stake": 14825,
        "win": 100810
      },
      {
        "bookmaker": "AbaBet",
        "outcome": "Away",
        "odd": 6.25,
        "stake": 16129,
        "win": 100806
      }
    ],
    "market_type": "1x2",
    "market_specifier": ""
  },
  {
    "match": "dila gori vs apollon",
    "sport": "Football",
    "type": "3-way",
    "profit_percent": 12.73,
    "profit_ugx": 12727,
    "total_stake": 100000,
    "arb_sum": 0.8727,
    "bets": [
      {
        "bookmaker": "AbaBet",
        "outcome": "Home",
        "odd": 3.75,
        "stake": 30556,
        "win": 114585
      },
      {
        "bookmaker": "Fortebet",
        "outcome": "Draw",
        "odd": 3.3,
        "stake": 34722,
        "win": 114583
      },
      {
        "bookmaker": "1xBet",
        "outcome": "Away",
        "odd": 3.3,
        "stake": 34722,
        "win": 114583
      }
    ],
    "market_type": "1x2",
    "market_specifier": ""
  },
  {
    "match": "paide vs zira",
    "sport": "Football",
    "type": "3-way",
    "profit_percent": 45.16,
    "profit_ugx": 45159,
    "total_stake": 100000,
    "arb_sum": 0.5484,
    "bets": [
      {
        "bookmaker": "Fortebet",
        "outcome": "Home",
        "odd": 7.2,
        "stake": 25326,
        "win": 182347
      },
      {
        "bookmaker": "AbaBet",
        "outcome": "Draw",
        "odd": 4.33,
        "stake": 42112,
        "win": 182345
      },
      {
        "bookmaker": "1xBet",
        "outcome": "Away",
        "odd": 5.6,
        "stake": 32562,
        "win": 182347
      }
    ],
    "market_type": "1x2",
    "market_specifier": ""
  },
  {
    "match": "rakow vs valletta",
    "sport": "Football",
    "type": "3-way",
    "profit_percent": 0.51,
    "profit_ugx": 508,
    "total_stake": 100000,
    "arb_sum": 0.9949,
    "bets": [
      {
        "bookmaker": "AbaBet",
        "outcome": "Home",
        "odd": 1.11,
        "stake": 90550,
        "win": 100511
      },
      {
        "bookmaker": "1xBet",
        "outcome": "Draw",
        "odd": 26.0,
        "stake": 3866,
        "win": 100516
      },
      {
        "bookmaker": "Fortebet",
        "outcome": "Away",
        "odd": 18.0,
        "stake": 5584,
        "win": 100512
      }
    ],
    "market_type": "1x2",
    "market_specifier": ""
  },
  {
    "match": "sheriff tiraspol vs maccabi tel aviv",
    "sport": "Football",
    "type": "3-way",
    "profit_percent": 7.2,
    "profit_ugx": 7204,
    "total_stake": 100000,
    "arb_sum": 0.928,
    "bets": [
      {
        "bookmaker": "Melbet",
        "outcome": "Home",
        "odd": 3.155,
        "stake": 34156,
        "win": 107762
      },
      {
        "bookmaker": "AbaBet",
        "outcome": "Draw",
        "odd": 3.2,
        "stake": 33676,
        "win": 107763
      },
      {
        "bookmaker": "22Bet",
        "outcome": "Away",
        "odd": 3.35,
        "stake": 32168,
        "win": 107763
      }
    ],
    "market_type": "1x2",
    "market_specifier": ""
  },
  {
    "match": "tromso vs hradec kralove",
    "sport": "Football",
    "type": "3-way",
    "profit_percent": 2.05,
    "profit_ugx": 2045,
    "total_stake": 100000,
    "arb_sum": 0.9795,
    "bets": [
      {
        "bookmaker": "AbaBet",
        "outcome": "Home",
        "odd": 1.45,
        "stake": 70406,
        "win": 102089
      },
      {
        "bookmaker": "Melbet",
        "outcome": "Draw",
        "odd": 6.54,
        "stake": 15610,
        "win": 102089
      },
      {
        "bookmaker": "ChampionBet",
        "outcome": "Away",
        "odd": 7.3,
        "stake": 13985,
        "win": 102090
      }
    ],
    "market_type": "1x2",
    "market_specifier": ""
  },
  {
    "match": "gais vs nordsjaelland",
    "sport": "Football",
    "type": "3-way",
    "profit_percent": 2.01,
    "profit_ugx": 2005,
    "total_stake": 100000,
    "arb_sum": 0.9799,
    "bets": [
      {
        "bookmaker": "AbaBet",
        "outcome": "Home",
        "odd": 2.7,
        "stake": 37795,
        "win": 102046
      },
      {
        "bookmaker": "ChampionBet",
        "outcome": "Draw",
        "odd": 3.17,
        "stake": 32191,
        "win": 102045
      },
      {
        "bookmaker": "1xBet",
        "outcome": "Away",
        "odd": 3.4,
        "stake": 30014,
        "win": 102048
      }
    ],
    "market_type": "1x2",
    "market_specifier": ""
  },
  {
    "match": "zimbru chisinau vs noah",
    "sport": "Football",
    "type": "3-way",
    "profit_percent": 24.59,
    "profit_ugx": 24586,
    "total_stake": 100000,
    "arb_sum": 0.7541,
    "bets": [
      {
        "bookmaker": "Fortebet",
        "outcome": "Home",
        "odd": 4.65,
        "stake": 28516,
        "win": 132599
      },
      {
        "bookmaker": "AbaBet",
        "outcome": "Draw",
        "odd": 3.7,
        "stake": 35838,
        "win": 132601
      },
      {
        "bookmaker": "1xBet",
        "outcome": "Away",
        "odd": 3.72,
        "stake": 35645,
        "win": 132599
      }
    ],
    "market_type": "1x2",
    "market_specifier": ""
  },
  {
    "match": "vaduz vs atletic escaldes",
    "sport": "Football",
    "type": "3-way",
    "profit_percent": 1.4,
    "profit_ugx": 1399,
    "total_stake": 100000,
    "arb_sum": 0.986,
    "bets": [
      {
        "bookmaker": "AbaBet",
        "outcome": "Home",
        "odd": 1.3,
        "stake": 78014,
        "win": 101418
      },
      {
        "bookmaker": "1xBet",
        "outcome": "Draw",
        "odd": 9.95,
        "stake": 10193,
        "win": 101420
      },
      {
        "bookmaker": "Fortebet",
        "outcome": "Away",
        "odd": 8.6,
        "stake": 11793,
        "win": 101420
      }
    ],
    "market_type": "1x2",
    "market_specifier": ""
  },
  {
    "match": "fcsb vs auda",
    "sport": "Football",
    "type": "3-way",
    "profit_percent": 2.67,
    "profit_ugx": 2674,
    "total_stake": 100000,
    "arb_sum": 0.9733,
    "bets": [
      {
        "bookmaker": "AbaBet",
        "outcome": "Home",
        "odd": 1.2,
        "stake": 85623,
        "win": 102748
      },
      {
        "bookmaker": "1xBet",
        "outcome": "Draw",
        "odd": 14.6,
        "stake": 7038,
        "win": 102755
      },
      {
        "bookmaker": "Fortebet",
        "outcome": "Away",
        "odd": 14.0,
        "stake": 7339,
        "win": 102746
      }
    ],
    "market_type": "1x2",
    "market_specifier": ""
  },
  {
    "match": "aluminij vs dinamo tirana",
    "sport": "Football",
    "type": "3-way",
    "profit_percent": 2.34,
    "profit_ugx": 2341,
    "total_stake": 100000,
    "arb_sum": 0.9766,
    "bets": [
      {
        "bookmaker": "Fortebet",
        "outcome": "Home",
        "odd": 2.66,
        "stake": 38495,
        "win": 102397
      },
      {
        "bookmaker": "AbaBet",
        "outcome": "Draw",
        "odd": 3.3,
        "stake": 31029,
        "win": 102396
      },
      {
        "bookmaker": "1xBet",
        "outcome": "Away",
        "odd": 3.36,
        "stake": 30475,
        "win": 102396
      }
    ],
    "market_type": "1x2",
    "market_specifier": ""
  },
  {
    "match": "vojvodina vs ajax",
    "sport": "Football",
    "type": "3-way",
    "profit_percent": 32.11,
    "profit_ugx": 32112,
    "total_stake": 100000,
    "arb_sum": 0.6789,
    "bets": [
      {
        "bookmaker": "Fortebet",
        "outcome": "Home",
        "odd": 5.6,
        "stake": 26304,
        "win": 147302
      },
      {
        "bookmaker": "AbaBet",
        "outcome": "Draw",
        "odd": 3.9,
        "stake": 37769,
        "win": 147299
      },
      {
        "bookmaker": "1xBet",
        "outcome": "Away",
        "odd": 4.1,
        "stake": 35927,
        "win": 147301
      }
    ],
    "market_type": "1x2",
    "market_specifier": ""
  },
  {
    "match": "st gallen vs benfica",
    "sport": "Football",
    "type": "3-way",
    "profit_percent": 43.72,
    "profit_ugx": 43724,
    "total_stake": 100000,
    "arb_sum": 0.5628,
    "bets": [
      {
        "bookmaker": "Melbet",
        "outcome": "Home",
        "odd": 7.17,
        "stake": 24783,
        "win": 177694
      },
      {
        "bookmaker": "Fortebet",
        "outcome": "Draw",
        "odd": 4.75,
        "stake": 37409,
        "win": 177693
      },
      {
        "bookmaker": "22Bet",
        "outcome": "Away",
        "odd": 4.7,
        "stake": 37807,
        "win": 177693
      }
    ],
    "market_type": "1x2",
    "market_specifier": ""
  },
  {
    "match": "chapecoense vs flamengo rj",
    "sport": "Football",
    "type": "3-way",
    "profit_percent": 44.79,
    "profit_ugx": 44787,
    "total_stake": 100000,
    "arb_sum": 0.5521,
    "bets": [
      {
        "bookmaker": "Melbet",
        "outcome": "Home",
        "odd": 8.3,
        "stake": 21821,
        "win": 181114
      },
      {
        "bookmaker": "Fortebet",
        "outcome": "Draw",
        "odd": 4.55,
        "stake": 39806,
        "win": 181117
      },
      {
        "bookmaker": "22Bet",
        "outcome": "Away",
        "odd": 4.72,
        "stake": 38372,
        "win": 181116
      }
    ],
    "market_type": "1x2",
    "market_specifier": ""
  },
  {
    "match": "internacional vs cruzeiro mg",
    "sport": "Football",
    "type": "3-way",
    "profit_percent": 0.98,
    "profit_ugx": 977,
    "total_stake": 100000,
    "arb_sum": 0.9902,
    "bets": [
      {
        "bookmaker": "Melbet",
        "outcome": "Home",
        "odd": 2.465,
        "stake": 40968,
        "win": 100986
      },
      {
        "bookmaker": "Fortebet",
        "outcome": "Draw",
        "odd": 3.35,
        "stake": 30145,
        "win": 100986
      },
      {
        "bookmaker": "1xBet",
        "outcome": "Away",
        "odd": 3.496,
        "stake": 28886,
        "win": 100985
      }
    ],
    "market_type": "1x2",
    "market_specifier": ""
  },
  {
    "match": "nashville vs montreal impact",
    "sport": "Football",
    "type": "3-way",
    "profit_percent": 2.23,
    "profit_ugx": 2234,
    "total_stake": 100000,
    "arb_sum": 0.9777,
    "bets": [
      {
        "bookmaker": "Melbet",
        "outcome": "Home",
        "odd": 1.552,
        "stake": 65905,
        "win": 102285
      },
      {
        "bookmaker": "22Bet",
        "outcome": "Draw",
        "odd": 6.0,
        "stake": 17047,
        "win": 102282
      },
      {
        "bookmaker": "AbaBet",
        "outcome": "Away",
        "odd": 6.0,
        "stake": 17047,
        "win": 102282
      }
    ],
    "market_type": "1x2",
    "market_specifier": ""
  },
  {
    "match": "austin vs seattle sounders",
    "sport": "Football",
    "type": "3-way",
    "profit_percent": 8.67,
    "profit_ugx": 8670,
    "total_stake": 100000,
    "arb_sum": 0.9133,
    "bets": [
      {
        "bookmaker": "Fortebet",
        "outcome": "Home",
        "odd": 2.97,
        "stake": 36866,
        "win": 109492
      },
      {
        "bookmaker": "AbaBet",
        "outcome": "Draw",
        "odd": 3.4,
        "stake": 32204,
        "win": 109494
      },
      {
        "bookmaker": "Melbet",
        "outcome": "Away",
        "odd": 3.54,
        "stake": 30930,
        "win": 109492
      }
    ],
    "market_type": "1x2",
    "market_specifier": ""
  },
  {
    "match": "portland timbers vs dallas",
    "sport": "Football",
    "type": "3-way",
    "profit_percent": 3.9,
    "profit_ugx": 3897,
    "total_stake": 100000,
    "arb_sum": 0.961,
    "bets": [
      {
        "bookmaker": "Fortebet",
        "outcome": "Home",
        "odd": 2.37,
        "stake": 43905,
        "win": 104055
      },
      {
        "bookmaker": "AbaBet",
        "outcome": "Draw",
        "odd": 3.7,
        "stake": 28123,
        "win": 104055
      },
      {
        "bookmaker": "Melbet",
        "outcome": "Away",
        "odd": 3.72,
        "stake": 27972,
        "win": 104056
      }
    ],
    "market_type": "1x2",
    "market_specifier": ""
  },
  {
    "match": "kansas vs minnesota",
    "sport": "Football",
    "type": "3-way",
    "profit_percent": 12.48,
    "profit_ugx": 12478,
    "total_stake": 100000,
    "arb_sum": 0.8752,
    "bets": [
      {
        "bookmaker": "Melbet",
        "outcome": "Home",
        "odd": 2.975,
        "stake": 38406,
        "win": 114258
      },
      {
        "bookmaker": "Fortebet",
        "outcome": "Draw",
        "odd": 3.7,
        "stake": 30880,
        "win": 114256
      },
      {
        "bookmaker": "22Bet",
        "outcome": "Away",
        "odd": 3.72,
        "stake": 30714,
        "win": 114256
      }
    ],
    "market_type": "1x2",
    "market_specifier": ""
  },
  {
    "match": "home special bets vs away special bets",
    "sport": "Football",
    "type": "3-way",
    "profit_percent": 18.3,
    "profit_ugx": 18304,
    "total_stake": 100000,
    "arb_sum": 0.817,
    "bets": [
      {
        "bookmaker": "Melbet",
        "outcome": "Home",
        "odd": 2.161,
        "stake": 56643,
        "win": 122406
      },
      {
        "bookmaker": "22Bet",
        "outcome": "Draw",
        "odd": 4.035,
        "stake": 30336,
        "win": 122406
      },
      {
        "bookmaker": "1xBet",
        "outcome": "Away",
        "odd": 9.4,
        "stake": 13022,
        "win": 122407
      }
    ],
    "market_type": "1x2",
    "market_specifier": ""
  },
  {
    "match": "home special bets vs away special bets",
    "sport": "Football",
    "type": "Asian Handicap -0.5",
    "profit_percent": 18.68,
    "profit_ugx": 18676,
    "total_stake": 100000,
    "arb_sum": 0.8132,
    "bets": [
      {
        "bookmaker": "1xBet",
        "outcome": "AH -0.5 (Home)",
        "odd": 2.106,
        "stake": 58388,
        "win": 122965
      },
      {
        "bookmaker": "22Bet",
        "outcome": "AH -0.5 (Away)",
        "odd": 2.955,
        "stake": 41612,
        "win": 122963
      }
    ],
    "market_type": "1x2",
    "market_specifier": ""
  },
  {
    "match": "home special bets vs away special bets",
    "sport": "Football",
    "type": "Asian Handicap -0.5",
    "profit_percent": 18.68,
    "profit_ugx": 18676,
    "total_stake": 100000,
    "arb_sum": 0.8132,
    "bets": [
      {
        "bookmaker": "1xBet",
        "outcome": "AH -0.5 (Home)",
        "odd": 2.106,
        "stake": 58388,
        "win": 122965
      },
      {
        "bookmaker": "22Bet",
        "outcome": "AH -0.5 (Away)",
        "odd": 2.955,
        "stake": 41612,
        "win": 122963
      }
    ],
    "market_type": "1x2",
    "market_specifier": ""
  },
  {
    "match": "chapecoense vs flamengo",
    "sport": "Football",
    "type": "Double Chance 1X",
    "profit_percent": 10.66,
    "profit_ugx": 10664,
    "total_stake": 100000,
    "arb_sum": 0.8934,
    "bets": [
      {
        "bookmaker": "1xBet",
        "outcome": "1X",
        "odd": 3.016,
        "stake": 37114,
        "win": 111936
      },
      {
        "bookmaker": "22Bet",
        "outcome": "X2",
        "odd": 1.78,
        "stake": 62886,
        "win": 111937
      }
    ],
    "market_type": "1x2",
    "market_specifier": ""
  },
  {
    "match": "chapecoense vs flamengo",
    "sport": "Football",
    "type": "Double Chance 1X",
    "profit_percent": 10.66,
    "profit_ugx": 10664,
    "total_stake": 100000,
    "arb_sum": 0.8934,
    "bets": [
      {
        "bookmaker": "22Bet",
        "outcome": "1X",
        "odd": 3.016,
        "stake": 37114,
        "win": 111936
      },
      {
        "bookmaker": "1xBet",
        "outcome": "X2",
        "odd": 1.78,
        "stake": 62886,
        "win": 111937
      }
    ],
    "market_type": "1x2",
    "market_specifier": ""
  },
  {
    "match": "st gallen vs benfica",
    "sport": "Football",
    "type": "Double Chance 1X",
    "profit_percent": 13.92,
    "profit_ugx": 13924,
    "total_stake": 100000,
    "arb_sum": 0.8608,
    "bets": [
      {
        "bookmaker": "1xBet",
        "outcome": "1X",
        "odd": 2.84,
        "stake": 40907,
        "win": 116176
      },
      {
        "bookmaker": "22Bet",
        "outcome": "X2",
        "odd": 1.966,
        "stake": 59093,
        "win": 116177
      }
    ],
    "market_type": "1x2",
    "market_specifier": ""
  },
  {
    "match": "st gallen vs benfica",
    "sport": "Football",
    "type": "Double Chance 1X",
    "profit_percent": 13.92,
    "profit_ugx": 13924,
    "total_stake": 100000,
    "arb_sum": 0.8608,
    "bets": [
      {
        "bookmaker": "22Bet",
        "outcome": "1X",
        "odd": 2.84,
        "stake": 40907,
        "win": 116176
      },
      {
        "bookmaker": "1xBet",
        "outcome": "X2",
        "odd": 1.966,
        "stake": 59093,
        "win": 116177
      }
    ],
    "market_type": "1x2",
    "market_specifier": ""
  }
]