[
  {
    "match": "halmstads bk vs bk hacken",
    "sport": "Football",
    "type": "3-way",
    "profit_percent": 33.77,
    "profit_ugx": 33766,
    "total_stake": 100000,
    "arb_sum": 0.6623,
    "bets": [
      {
        "bookmaker": "Fortebet",
        "outcome": "Home",
        "odd": 4.95,
        "stake": 30501,
        "win": 150980
      },
      {
        "bookmaker": "AbaBet",
        "outcome": "Draw",
        "odd": 4.2,
        "stake": 35948,
        "win": 150982
      },
      {
        "bookmaker": "22Bet",
        "outcome": "Away",
        "odd": 4.5,
        "stake": 33551,
        "win": 150980
      }
    ],
    "market_type": "1x2",
    "market_specifier": ""
  },
  {
    "match": "hammarby if vs degerfors if",
    "sport": "Football",
    "type": "3-way",
    "profit_percent": 0.75,
    "profit_ugx": 748,
    "total_stake": 100000,
    "arb_sum": 0.9925,
    "bets": [
      {
        "bookmaker": "22Bet",
        "outcome": "Home",
        "odd": 1.206,
        "stake": 83544,
        "win": 100754
      },
      {
        "bookmaker": "1xBet",
        "outcome": "Draw",
        "odd": 12.5,
        "stake": 8060,
        "win": 100750
      },
      {
        "bookmaker": "Fortebet",
        "outcome": "Away",
        "odd": 12.0,
        "stake": 8396,
        "win": 100752
      }
    ],
    "market_type": "1x2",
    "market_specifier": ""
  },
  {
    "match": "if elfsborg vs ik sirius",
    "sport": "Football",
    "type": "3-way",
    "profit_percent": 18.91,
    "profit_ugx": 18911,
    "total_stake": 100000,
    "arb_sum": 0.8109,
    "bets": [
      {
        "bookmaker": "22Bet",
        "outcome": "Home",
        "odd": 3.69,
        "stake": 33420,
        "win": 123320
      },
      {
        "bookmaker": "Fortebet",
        "outcome": "Draw",
        "odd": 3.75,
        "stake": 32886,
        "win": 123322
      },
      {
        "bookmaker": "1xBet",
        "outcome": "Away",
        "odd": 3.66,
        "stake": 33694,
        "win": 123320
      }
    ],
    "market_type": "1x2",
    "market_specifier": ""
  },
  {
    "match": "ff jaro vs inter turku",
    "sport": "Football",
    "type": "3-way",
    "profit_percent": 24.64,
    "profit_ugx": 24641,
    "total_stake": 100000,
    "arb_sum": 0.7536,
    "bets": [
      {
        "bookmaker": "Fortebet",
        "outcome": "Home",
        "odd": 4.4,
        "stake": 30159,
        "win": 132700
      },
      {
        "bookmaker": "AbaBet",
        "outcome": "Draw",
        "odd": 3.8,
        "stake": 34921,
        "win": 132700
      },
      {
        "bookmaker": "22Bet",
        "outcome": "Away",
        "odd": 3.8,
        "stake": 34921,
        "win": 132700
      }
    ],
    "market_type": "1x2",
    "market_specifier": ""
  },
  {
    "match": "spain vs argentina",
    "sport": "Football",
    "type": "3-way",
    "profit_percent": 2.02,
    "profit_ugx": 2018,
    "total_stake": 100000,
    "arb_sum": 0.9798,
    "bets": [
      {
        "bookmaker": "Melbet",
        "outcome": "Home",
        "odd": 2.275,
        "stake": 44861,
        "win": 102059
      },
      {
        "bookmaker": "22Bet",
        "outcome": "Draw",
        "odd": 3.655,
        "stake": 27923,
        "win": 102059
      },
      {
        "bookmaker": "Fortebet",
        "outcome": "Away",
        "odd": 3.75,
        "stake": 27216,
        "win": 102060
      }
    ],
    "market_type": "1x2",
    "market_specifier": ""
  },
  {
    "match": "1 monheim vs siegburger sv 04",
    "sport": "Football",
    "type": "3-way",
    "profit_percent": 28.15,
    "profit_ugx": 28147,
    "total_stake": 100000,
    "arb_sum": 0.7185,
    "bets": [
      {
        "bookmaker": "22Bet",
        "outcome": "Home",
        "odd": 3.53,
        "stake": 39426,
        "win": 139174
      },
      {
        "bookmaker": "AbaBet",
        "outcome": "Draw",
        "odd": 4.75,
        "stake": 29300,
        "win": 139175
      },
      {
        "bookmaker": "1xBet",
        "outcome": "Away",
        "odd": 4.45,
        "stake": 31275,
        "win": 139174
      }
    ],
    "market_type": "1x2",
    "market_specifier": ""
  },
  {
    "match": "ifk varnamo vs ljungskile sk",
    "sport": "Football",
    "type": "3-way",
    "profit_percent": 1.37,
    "profit_ugx": 1372,
    "total_stake": 100000,
    "arb_sum": 0.9863,
    "bets": [
      {
        "bookmaker": "AbaBet",
        "outcome": "Home",
        "odd": 2.45,
        "stake": 41384,
        "win": 101391
      },
      {
        "bookmaker": "SportyBet",
        "outcome": "Draw",
        "odd": 3.5,
        "stake": 28969,
        "win": 101392
      },
      {
        "bookmaker": "22Bet",
        "outcome": "Away",
        "odd": 3.42,
        "stake": 29647,
        "win": 101393
      }
    ],
    "market_type": "1x2",
    "market_specifier": ""
  },
  {
    "match": "concordia vs barra",
    "sport": "Football",
    "type": "3-way",
    "profit_percent": 23.06,
    "profit_ugx": 23065,
    "total_stake": 100000,
    "arb_sum": 0.7694,
    "bets": [
      {
        "bookmaker": "AbaBet",
        "outcome": "Home",
        "odd": 4.33,
        "stake": 30018,
        "win": 129978
      },
      {
        "bookmaker": "SportyBet",
        "outcome": "Draw",
        "odd": 3.75,
        "stake": 34661,
        "win": 129979
      },
      {
        "bookmaker": "1xBet",
        "outcome": "Away",
        "odd": 3.68,
        "stake": 35320,
        "win": 129978
      }
    ],
    "market_type": "1x2",
    "market_specifier": ""
  },
  {
    "match": "ks cracovia krakow vs sevilla",
    "sport": "Football",
    "type": "3-way",
    "profit_percent": 4.89,
    "profit_ugx": 4888,
    "total_stake": 100000,
    "arb_sum": 0.9511,
    "bets": [
      {
        "bookmaker": "22Bet",
        "outcome": "Home",
        "odd": 3.055,
        "stake": 34416,
        "win": 105141
      },
      {
        "bookmaker": "Fortebet",
        "outcome": "Draw",
        "odd": 3.1,
        "stake": 33916,
        "win": 105140
      },
      {
        "bookmaker": "1xBet",
        "outcome": "Away",
        "odd": 3.32,
        "stake": 31669,
        "win": 105141
      }
    ],
    "market_type": "1x2",
    "market_specifier": ""
  },
  {
    "match": "sporting hasselt vs royal antwerp",
    "sport": "Football",
    "type": "3-way",
    "profit_percent": 19.55,
    "profit_ugx": 19554,
    "total_stake": 100000,
    "arb_sum": 0.8045,
    "bets": [
      {
        "bookmaker": "22Bet",
        "outcome": "Home",
        "odd": 3.9,
        "stake": 31874,
        "win": 124309
      },
      {
        "bookmaker": "SportyBet",
        "outcome": "Draw",
        "odd": 3.6,
        "stake": 34530,
        "win": 124308
      },
      {
        "bookmaker": "1xBet",
        "outcome": "Away",
        "odd": 3.7,
        "stake": 33597,
        "win": 124309
      }
    ],
    "market_type": "1x2",
    "market_specifier": ""
  },
  {
    "match": "genoa vs trento scsd",
    "sport": "Football",
    "type": "3-way",
    "profit_percent": 1.28,
    "profit_ugx": 1282,
    "total_stake": 100000,
    "arb_sum": 0.9872,
    "bets": [
      {
        "bookmaker": "AbaBet",
        "outcome": "Home",
        "odd": 1.17,
        "stake": 86580,
        "win": 101299
      },
      {
        "bookmaker": "22Bet",
        "outcome": "Draw",
        "odd": 18.0,
        "stake": 5628,
        "win": 101304
      },
      {
        "bookmaker": "Fortebet",
        "outcome": "Away",
        "odd": 13.0,
        "stake": 7792,
        "win": 101296
      }
    ],
    "market_type": "1x2",
    "market_specifier": ""
  },
  {
    "match": "bicskei vs dunaharaszti",
    "sport": "Football",
    "type": "3-way",
    "profit_percent": 1.65,
    "profit_ugx": 1646,
    "total_stake": 100000,
    "arb_sum": 0.9835,
    "bets": [
      {
        "bookmaker": "22Bet",
        "outcome": "Home",
        "odd": 2.39,
        "stake": 42541,
        "win": 101673
      },
      {
        "bookmaker": "AbaBet",
        "outcome": "Draw",
        "odd": 3.6,
        "stake": 28243,
        "win": 101675
      },
      {
        "bookmaker": "1xBet",
        "outcome": "Away",
        "odd": 3.48,
        "stake": 29216,
        "win": 101672
      }
    ],
    "market_type": "1x2",
    "market_specifier": ""
  },
  {
    "match": "algeria w vs zambia w",
    "sport": "Football",
    "type": "3-way",
    "profit_percent": 21.21,
    "profit_ugx": 21211,
    "total_stake": 100000,
    "arb_sum": 0.7879,
    "bets": [
      {
        "bookmaker": "1xBet",
        "outcome": "Home",
        "odd": 2.23,
        "stake": 56915,
        "win": 126920
      },
      {
        "bookmaker": "Melbet",
        "outcome": "Draw",
        "odd": 9.6,
        "stake": 13221,
        "win": 126922
      },
      {
        "bookmaker": "22Bet",
        "outcome": "Away",
        "odd": 4.25,
        "stake": 29864,
        "win": 126922
      }
    ],
    "market_type": "1x2",
    "market_specifier": ""
  },
  {
    "match": "ff jaro vs inter turku",
    "sport": "Football",
    "type": "Double Chance 1X",
    "profit_percent": 4.03,
    "profit_ugx": 4032,
    "total_stake": 100000,
    "arb_sum": 0.9597,
    "bets": [
      {
        "bookmaker": "1xBet",
        "outcome": "1X",
        "odd": 2.04,
        "stake": 51079,
        "win": 104201
      },
      {
        "bookmaker": "22Bet",
        "outcome": "X2",
        "odd": 2.13,
        "stake": 48921,
        "win": 104202
      }
    ],
    "market_type": "1x2",
    "market_specifier": ""
  },
  {
    "match": "ff jaro vs inter turku",
    "sport": "Football",
    "type": "Double Chance 1X",
    "profit_percent": 4.03,
    "profit_ugx": 4032,
    "total_stake": 100000,
    "arb_sum": 0.9597,
    "bets": [
      {
        "bookmaker": "22Bet",
        "outcome": "1X",
        "odd": 2.04,
        "stake": 51079,
        "win": 104201
      },
      {
        "bookmaker": "1xBet",
        "outcome": "X2",
        "odd": 2.13,
        "stake": 48921,
        "win": 104202
      }
    ],
    "market_type": "1x2",
    "market_specifier": ""
  },
  {
    "match": "elfsborg vs sirius",
    "sport": "Football",
    "type": "Double Chance 1X",
    "profit_percent": 2.41,
    "profit_ugx": 2411,
    "total_stake": 100000,
    "arb_sum": 0.9759,
    "bets": [
      {
        "bookmaker": "1xBet",
        "outcome": "1X",
        "odd": 1.85,
        "stake": 55389,
        "win": 102470
      },
      {
        "bookmaker": "22Bet",
        "outcome": "X2",
        "odd": 2.297,
        "stake": 44611,
        "win": 102471
      }
    ],
    "market_type": "1x2",
    "market_specifier": ""
  },
  {
    "match": "elfsborg vs sirius",
    "sport": "Football",
    "type": "Double Chance 1X",
    "profit_percent": 2.41,
    "profit_ugx": 2411,
    "total_stake": 100000,
    "arb_sum": 0.9759,
    "bets": [
      {
        "bookmaker": "22Bet",
        "outcome": "1X",
        "odd": 1.85,
        "stake": 55389,
        "win": 102470
      },
      {
        "bookmaker": "1xBet",
        "outcome": "X2",
        "odd": 2.297,
        "stake": 44611,
        "win": 102471
      }
    ],
    "market_type": "1x2",
    "market_specifier": ""
  },
  {
    "match": "halmstads vs hacken",
    "sport": "Football",
    "type": "Double Chance 1X",
    "profit_percent": 15.67,
    "profit_ugx": 15665,
    "total_stake": 100000,
    "arb_sum": 0.8433,
    "bets": [
      {
        "bookmaker": "1xBet",
        "outcome": "1X",
        "odd": 2.375,
        "stake": 49926,
        "win": 118574
      },
      {
        "bookmaker": "22Bet",
        "outcome": "X2",
        "odd": 2.368,
        "stake": 50074,
        "win": 118575
      }
    ],
    "market_type": "1x2",
    "market_specifier": ""
  },
  {
    "match": "halmstads vs hacken",
    "sport": "Football",
    "type": "Double Chance 1X",
    "profit_percent": 15.67,
    "profit_ugx": 15665,
    "total_stake": 100000,
    "arb_sum": 0.8433,
    "bets": [
      {
        "bookmaker": "22Bet",
        "outcome": "1X",
        "odd": 2.375,
        "stake": 49926,
        "win": 118574
      },
      {
        "bookmaker": "1xBet",
        "outcome": "X2",
        "odd": 2.368,
        "stake": 50074,
        "win": 118575
      }
    ],
    "market_type": "1x2",
    "market_specifier": ""
  },
  {
    "match": "monheim vs siegburger sv 04",
    "sport": "Football",
    "type": "Double Chance 1X",
    "profit_percent": 15.65,
    "profit_ugx": 15646,
    "total_stake": 100000,
    "arb_sum": 0.8435,
    "bets": [
      {
        "bookmaker": "1xBet",
        "outcome": "1X",
        "odd": 1.96,
        "stake": 60484,
        "win": 118549
      },
      {
        "bookmaker": "22Bet",
        "outcome": "X2",
        "odd": 3.0,
        "stake": 39516,
        "win": 118548
      }
    ],
    "market_type": "1x2",
    "market_specifier": ""
  },
  {
    "match": "monheim vs siegburger sv 04",
    "sport": "Football",
    "type": "Double Chance 1X",
    "profit_percent": 15.65,
    "profit_ugx": 15646,
    "total_stake": 100000,
    "arb_sum": 0.8435,
    "bets": [
      {
        "bookmaker": "22Bet",
        "outcome": "1X",
        "odd": 1.96,
        "stake": 60484,
        "win": 118549
      },
      {
        "bookmaker": "1xBet",
        "outcome": "X2",
        "odd": 3.0,
        "stake": 39516,
        "win": 118548
      }
    ],
    "market_type": "1x2",
    "market_specifier": ""
  },
  {
    "match": "vfb homberg vs fortuna dusseldorf ii",
    "sport": "Football",
    "type": "Double Chance 1X",
    "profit_percent": 29.28,
    "profit_ugx": 29284,
    "total_stake": 100000,
    "arb_sum": 0.7072,
    "bets": [
      {
        "bookmaker": "1xBet",
        "outcome": "1X",
        "odd": 3.42,
        "stake": 41348,
        "win": 141410
      },
      {
        "bookmaker": "22Bet",
        "outcome": "X2",
        "odd": 2.411,
        "stake": 58652,
        "win": 141410
      }
    ],
    "market_type": "1x2",
    "market_specifier": ""
  },
  {
    "match": "vfb homberg vs fortuna dusseldorf ii",
    "sport": "Football",
    "type": "Double Chance 1X",
    "profit_percent": 29.28,
    "profit_ugx": 29284,
    "total_stake": 100000,
    "arb_sum": 0.7072,
    "bets": [
      {
        "bookmaker": "22Bet",
        "outcome": "1X",
        "odd": 3.42,
        "stake": 41348,
        "win": 141410
      },
      {
        "bookmaker": "1xBet",
        "outcome": "X2",
        "odd": 2.411,
        "stake": 58652,
        "win": 141410
      }
    ],
    "market_type": "1x2",
    "market_specifier": ""
  },
  {
    "match": "koninklijke sporting hasselt vs royal antwerp",
    "sport": "Football",
    "type": "Double Chance 1X",
    "profit_percent": 5.01,
    "profit_ugx": 5009,
    "total_stake": 100000,
    "arb_sum": 0.9499,
    "bets": [
      {
        "bookmaker": "1xBet",
        "outcome": "1X",
        "odd": 1.909,
        "stake": 55146,
        "win": 105274
      },
      {
        "bookmaker": "22Bet",
        "outcome": "X2",
        "odd": 2.347,
        "stake": 44854,
        "win": 105272
      }
    ],
    "market_type": "1x2",
    "market_specifier": ""
  },
  {
    "match": "koninklijke sporting hasselt vs royal antwerp",
    "sport": "Football",
    "type": "Double Chance 1X",
    "profit_percent": 5.01,
    "profit_ugx": 5009,
    "total_stake": 100000,
    "arb_sum": 0.9499,
    "bets": [
      {
        "bookmaker": "22Bet",
        "outcome": "1X",
        "odd": 1.909,
        "stake": 55146,
        "win": 105274
      },
      {
        "bookmaker": "1xBet",
        "outcome": "X2",
        "odd": 2.347,
        "stake": 44854,
        "win": 105272
      }
    ],
    "market_type": "1x2",
    "market_specifier": ""
  },
  {
    "match": "rudes vs shakhtar donetsk",
    "sport": "Football",
    "type": "Double Chance 1X",
    "profit_percent": 10.09,
    "profit_ugx": 10085,
    "total_stake": 100000,
    "arb_sum": 0.8991,
    "bets": [
      {
        "bookmaker": "1xBet",
        "outcome": "1X",
        "odd": 3.37,
        "stake": 33002,
        "win": 111217
      },
      {
        "bookmaker": "22Bet",
        "outcome": "X2",
        "odd": 1.66,
        "stake": 66998,
        "win": 111217
      }
    ],
    "market_type": "1x2",
    "market_specifier": ""
  },
  {
    "match": "rudes vs shakhtar donetsk",
    "sport": "Football",
    "type": "Double Chance 1X",
    "profit_percent": 10.09,
    "profit_ugx": 10085,
    "total_stake": 100000,
    "arb_sum": 0.8991,
    "bets": [
      {
        "bookmaker": "22Bet",
        "outcome": "1X",
        "odd": 3.37,
        "stake": 33002,
        "win": 111217
      },
      {
        "bookmaker": "1xBet",
        "outcome": "X2",
        "odd": 1.66,
        "stake": 66998,
        "win": 111217
      }
    ],
    "market_type": "1x2",
    "market_specifier": ""
  },
  {
    "match": "sturm graz ii vs alhilal riyadh",
    "sport": "Football",
    "type": "Double Chance 1X",
    "profit_percent": 21.23,
    "profit_ugx": 21229,
    "total_stake": 100000,
    "arb_sum": 0.7877,
    "bets": [
      {
        "bookmaker": "1xBet",
        "outcome": "1X",
        "odd": 4.8,
        "stake": 26448,
        "win": 126950
      },
      {
        "bookmaker": "22Bet",
        "outcome": "X2",
        "odd": 1.726,
        "stake": 73552,
        "win": 126951
      }
    ],
    "market_type": "1x2",
    "market_specifier": ""
  },
  {
    "match": "sturm graz ii vs alhilal riyadh",
    "sport": "Football",
    "type": "Double Chance 1X",
    "profit_percent": 21.23,
    "profit_ugx": 21229,
    "total_stake": 100000,
    "arb_sum": 0.7877,
    "bets": [
      {
        "bookmaker": "22Bet",
        "outcome": "1X",
        "odd": 4.8,
        "stake": 26448,
        "win": 126950
      },
      {
        "bookmaker": "1xBet",
        "outcome": "X2",
        "odd": 1.726,
        "stake": 73552,
        "win": 126951
      }
    ],
    "market_type": "1x2",
    "market_specifier": ""
  },
  {
    "match": "stk 1914 samorin vs algharafa",
    "sport": "Football",
    "type": "Double Chance 1X",
    "profit_percent": 6.6,
    "profit_ugx": 6595,
    "total_stake": 100000,
    "arb_sum": 0.934,
    "bets": [
      {
        "bookmaker": "1xBet",
        "outcome": "1X",
        "odd": 1.94,
        "stake": 55186,
        "win": 107061
      },
      {
        "bookmaker": "22Bet",
        "outcome": "X2",
        "odd": 2.389,
        "stake": 44814,
        "win": 107061
      }
    ],
    "market_type": "1x2",
    "market_specifier": ""
  },
  {
    "match": "stk 1914 samorin vs algharafa",
    "sport": "Football",
    "type": "Double Chance 1X",
    "profit_percent": 6.6,
    "profit_ugx": 6595,
    "total_stake": 100000,
    "arb_sum": 0.934,
    "bets": [
      {
        "bookmaker": "22Bet",
        "outcome": "1X",
        "odd": 1.94,
        "stake": 55186,
        "win": 107061
      },
      {
        "bookmaker": "1xBet",
        "outcome": "X2",
        "odd": 2.389,
        "stake": 44814,
        "win": 107061
      }
    ],
    "market_type": "1x2",
    "market_specifier": ""
  }
]